pyLogicx/__init__.py
pyLogicx/logger.py
pyLogicx/utils.py
pyLogicx-0.2.dist-info/METADATA
pyLogicx-0.2.dist-info/WHEEL
pyLogicx-0.2.dist-info/top_level.txt
pyLogicx-0.2.dist-info/RECORD
