Metadata-Version: 2.1
Name: pyLogicx
Version: 0.2
Summary: Utility functions and logging system.
Home-page: https://github.com/prasad-chavan1/pyLogix/
Author: Prasad Chavan
Author-email: prasadchavan1203@gmail.com
License: MIT
Platform: UNKNOWN
Classifier: Programming Language :: Python :: 3
Classifier: License :: OSI Approved :: MIT License
Classifier: Operating System :: OS Independent
Requires-Python: >=3.6
Requires-Dist: colorama
